gerrit_tools/__init__.py
gerrit_tools/bcolors.py
gerrit_tools/config.py
gerrit_tools/main.py
gerrit_tools-0.0.8.dist-info/METADATA
gerrit_tools-0.0.8.dist-info/WHEEL
gerrit_tools-0.0.8.dist-info/entry_points.txt
gerrit_tools-0.0.8.dist-info/top_level.txt
gerrit_tools-0.0.8.dist-info/RECORD
