Metadata-Version: 2.1
Name: gerrit-tools
Version: 0.0.8
Summary: Gerrit CLI Tool
Home-page: https://github.com/smotyrev/gerrit_tools
Author: Sergey Motyrev
Author-email: smotyrev@gmail.com
Platform: Any
Classifier: Intended Audience :: Developers
Classifier: Natural Language :: English
Classifier: License :: OSI Approved :: Apache Software License
Classifier: Programming Language :: Python
Classifier: Programming Language :: Python :: 3.5
Classifier: Environment :: Console
